Workbook
Name NativeTimeline_Date: #N/A
Name NativeTimeline_Date1: #N/A
Name Slicer_Branch: #N/A
Name Slicer_Customer_Type: #N/A
Name Slicer_Gender: #N/A
Name Slicer_Product_Line: #N/A

Sheet RAW
A1: Date | B1: Branch | C1: Customer type | D1: Gender | E1: Product line | F1: Unit price | G1: Quantity | H1: Payment | I1: Rating
A2: 45292 | B2: Brooklyn | C2: Member | D2: Female | E2: Food & Beverages | F2: 84.63 | G2: 10 | H2: Credit card | I2: 9
A3: 45292 | B3: Queens | C3: Normal | D3: Female | E3: Electronics | F3: 63.22 | G3: 2 | H3: Cash | I3: 8.5
A4: 45292 | B4: Brooklyn | C4: Normal | D4: Female | E4: Electronics | F4: 74.71 | G4: 6 | H4: Cash | I4: 6.7
A5: 45292 | B5: Queens | C5: Member | D5: Female | E5: Sports & Travel | F5: 36.98 | G5: 10 | H5: Credit card | I5: 7
A6: 45292 | B6: Manhattan | C6: Member | D6: Female | E6: Sports & Travel | F6: 27.04 | G6: 4 | H6: Ewallet | I6: 6.9
A7: 45292 | B7: Manhattan | C7: Normal | D7: Female | E7: Fashion & Accs | F7: 65.74 | G7: 9 | H7: Cash | I7: 7.7
A8: 45292 | B8: Manhattan | C8: Member | D8: Male | E8: Home & Lifestyle | F8: 47.59 | G8: 8 | H8: Cash | I8: 5.7
A9: 45292 | B9: Manhattan | C9: Normal | D9: Male | E9: Sports & Travel | F9: 72.61 | G9: 6 | H9: Credit card | I9: 6.9
A10: 45292 | B10: Queens | C10: Normal | D10: Male | E10: Health & Beauty | F10: 62.87 | G10: 2 | H10: Cash | I10: 5
A11: 45292 | B11: Brooklyn | C11: Normal | D11: Male | E11: Food & Beverages | F11: 21.12 | G11: 8 | H11: Cash | I11: 6.3
A12: 45292 | B12: Queens | C12: Member | D12: Female | E12: Sports & Travel | F12: 29.22 | G12: 6 | H12: Ewallet | I12: 5
A13: 45292 | B13: Manhattan | C13: Member | D13: Female | E13: Electronics | F13: 74.22 | G13: 10 | H13: Credit card | I13: 4.3
... A119: 45627 | B119: Brooklyn | C119: Normal | D119: Female | E119: Home & Lifestyle | F119: 51.07 | G119: 7 | H119: Cash | I119: 7
A120: 1/13/2024 | B120: Brooklyn | C120: Member | D120: Male | E120: Sports & Travel | F120: 72.6 | G120: 6 | H120: Cash | I120: 6.9
A121: 1/13/2024 | B121: Manhattan | C121: Member | D121: Male | E121: Home & Lifestyle | F121: 81.01 | G121: 3 | H121: Credit card | I121: 9.3
A122: 1/13/2024 | B122: Queens | C122: Member | D122: Female | E122: Fashion & Accs | F122: 74.29 | G122: 1 | H122: Cash | I122: 5
A123: 1/13/2024 | B123: Manhattan | C123: Normal | D123: Female | E123: Electronics | F123: 23.46 | G123: 6 | H123: Ewallet | I123: 6.4
A124: 1/13/2024 | B124: Manhattan | C124: Member | D124: Female | E124: Health & Beauty | F124: 39.62 | G124: 9 | H124: Credit card | I124: 6.8
A125: 1/13/2024 | B125: Queens | C125: Member | D125: Female | E125: Food & Beverages | F125: 21.04 | G125: 4 | H125: Cash | I125: 7.6
A126: 1/13/2024 | B126: Brooklyn | C126: Member | D126: Male | E126: Fashion & Accs | F126: 59.86 | G126: 2 | H126: Ewallet | I126: 6.7
A127: 1/13/2024 | B127: Brooklyn | C127: Normal | D127: Male | E127: Food & Beverages | F127: 72.39 | G127: 2 | H127: Credit card | I127: 8.1
A128: 1/13/2024 | B128: Manhattan | C128: Normal | D128: Male | E128: Sports & Travel | F128: 45.58 | G128: 7 | H128: Cash | I128: 5
A129: 1/13/2024 | B129: Queens | C129: Normal | D129: Female | E129: Electronics | F129: 41.65 | G129: 10 | H129: Credit card | I129: 5.4
A130: 1/14/2024 | B130: Queens | C130: Member | D130: Male | E130: Health & Beauty | F130: 60.47 | G130: 3 | H130: Credit card | I130: 5.6
A131: 1/14/2024 | B131: Brooklyn | C131: Normal | D131: Female | E131: Sports & Travel | F131: 34.81 | G131: 1 | H131: Credit card | I131: 7
... A353: 1/31/2024 | B353: Manhattan | C353: Member | D353: Male | E353: Electronics | F353: 66.35 | G353: 1 | H353: Credit card | I353: 9.7
A354: 45293 | B354: Queens | C354: Member | D354: Female | E354: Food & Beverages | F354: 87.48 | G354: 6 | H354: Ewallet | I354: 5.1
A355: 45293 | B355: Manhattan | C355: Member | D355: Female | E355: Food & Beverages | F355: 14.23 | G355: 5 | H355: Credit card | I355: 4.4
A356: 45293 | B356: Manhattan | C356: Member | D356: Male | E356: Sports & Travel | F356: 69.52 | G356: 7 | H356: Credit card | I356: 8.5
A357: 45293 | B357: Queens | C357: Normal | D357: Female | E357: Electronics | F357: 23.07 | G357: 9 | H357: Cash | I357: 4.9
A358: 45293 | B358: Queens | C358: Member | D358: Female | E358: Home & Lifestyle | F358: 80.79 | G358: 9 | H358: Credit card | I358: 9.5
A359: 45293 | B359: Manhattan | C359: Member | D359: Female | E359: Health & Beauty | F359: 77.68 | G359: 4 | H359: Cash | I359: 8.4
A360: 45324 | B360: Brooklyn | C360: Member | D360: Female | E360: Electronics | F360: 26.26 | G360: 7 | H360: Cash | I360: 9.9
A361: 45324 | B361: Manhattan | C361: Member | D361: Male | E361: Fashion & Accs | F361: 43.13 | G361: 10 | H361: Credit card | I361: 5.5
A362: 45324 | B362: Brooklyn | C362: Normal | D362: Female | E362: Fashion & Accs | F362: 25.56 | G362: 7 | H362: Cash | I362: 7.1
A363: 45324 | B363: Queens | C363: Member | D363: Female | E363: Food & Beverages | F363: 38.42 | G363: 1 | H363: Cash | I363: 8.6
A364: 45324 | B364: Queens | C364: Normal | D364: Male | E364: Food & Beverages | F364: 65.97 | G364: 8 | H364: Cash | I364: 8.4
A365: 45324 | B365: Manhattan | C365: Member | D365: Female | E365: Sports & Travel | F365: 51.52 | G365: 8 | H365: Cash | I365: 9.6
... A495: 45628 | B495: Manhattan | C495: Member | D495: Female | E495: Sports & Travel | F495: 71.63 | G495: 2 | H495: Ewallet | I495: 8.8
A496: 2/13/2024 | B496: Manhattan | C496: Member | D496: Male | E496: Electronics | F496: 76.82 | G496: 1 | H496: Ewallet | I496: 7.2
A497: 2/13/2024 | B497: Brooklyn | C497: Member | D497: Female | E497: Sports & Travel | F497: 20.18 | G497: 4 | H497: Credit card | I497: 5
A498: 2/13/2024 | B498: Queens | C498: Member | D498: Female | E498: Fashion & Accs | F498: 92.98 | G498: 2 | H498: Credit card | I498: 8
A499: 2/13/2024 | B499: Brooklyn | C499: Member | D499: Female | E499: Fashion & Accs | F499: 29.56 | G499: 5 | H499: Cash | I499: 6.9
A500: 2/13/2024 | B500: Queens | C500: Normal | D500: Female | E500: Fashion & Accs | F500: 22.51 | G500: 7 | H500: Credit card | I500: 4.8
A501: 2/13/2024 | B501: Queens | C501: Member | D501: Female | E501: Food & Beverages | F501: 14.87 | G501: 2 | H501: Credit card | I501: 8.9
A502: 2/13/2024 | B502: Manhattan | C502: Member | D502: Male | E502: Electronics | F502: 32.25 | G502: 4 | H502: Ewallet | I502: 6.5
A503: 2/13/2024 | B503: Brooklyn | C503: Normal | D503: Male | E503: Sports & Travel | F503: 13.69 | G503: 6 | H503: Cash | I503: 6.3
A504: 2/14/2024 | B504: Manhattan | C504: Member | D504: Male | E504: Health & Beauty | F504: 91.3 | G504: 1 | H504: Ewallet | I504: 9.2
A505: 2/14/2024 | B505: Manhattan | C505: Normal | D505: Male | E505: Sports & Travel | F505: 44.65 | G505: 3 | H505: Cash | I505: 6.2
A506: 2/14/2024 | B506: Brooklyn | C506: Member | D506: Male | E506: Health & Beauty | F506: 75.74 | G506: 4 | H506: Cash | I506: 7.6
A507: 2/14/2024 | B507: Brooklyn | C507: Member | D507: Female | E507: Sports & Travel | F507: 60.08 | G507: 7 | H507: Credit card | I507: 4.5
... A664: 2/29/2024 | B664: Manhattan | C664: Member | D664: Female | E664: Health & Beauty | F664: 10.16 | G664: 5 | H664: Ewallet | I664: 4.1
A665: 45294 | B665: Brooklyn | C665: Normal | D665: Male | E665: Electronics | F665: 27.5 | G665: 3 | H665: Ewallet | I665: 6.5
A666: 45294 | B666: Queens | C666: Member | D666: Female | E666: Food & Beverages | F666: 74.89 | G666: 4 | H666: Ewallet | I666: 4.2
A667: 45294 | B667: Manhattan | C667: Normal | D667: Female | E667: Electronics | F667: 45.48 | G667: 10 | H667: Credit card | I667: 4.8
A668: 45294 | B668: Brooklyn | C668: Member | D668: Male | E668: Food & Beverages | F668: 53.72 | G668: 1 | H668: Ewallet | I668: 6.4
A669: 45294 | B669: Brooklyn | C669: Member | D669: Male | E669: Fashion & Accs | F669: 81.31 | G669: 7 | H669: Ewallet | I669: 6.3
A670: 45294 | B670: Manhattan | C670: Normal | D670: Male | E670: Home & Lifestyle | F670: 34.73 | G670: 2 | H670: Ewallet | I670: 9.7
A671: 45294 | B671: Queens | C671: Normal | D671: Male | E671: Fashion & Accs | F671: 78.55 | G671: 9 | H671: Cash | I671: 7.2
A672: 45294 | B672: Manhattan | C672: Member | D672: Female | E672: Fashion & Accs | F672: 22.32 | G672: 4 | H672: Credit card | I672: 4.4
A673: 45294 | B673: Brooklyn | C673: Normal | D673: Male | E673: Health & Beauty | F673: 69.51 | G673: 2 | H673: Ewallet | I673: 8.1
A674: 45294 | B674: Brooklyn | C674: Normal | D674: Male | E674: Health & Beauty | F674: 14.82 | G674: 3 | H674: Credit card | I674: 8.7
A675: 45325 | B675: Brooklyn | C675: Member | D675: Female | E675: Electronics | F675: 26.26 | G675: 3 | H675: Ewallet | I675: 6.3
A676: 45325 | B676: Queens | C676: Member | D676: Female | E676: Sports & Travel | F676: 54.55 | G676: 10 | H676: Credit card | I676: 7.1
... A817: 45629 | B817: Brooklyn | C817: Member | D817: Male | E817: Health & Beauty | F817: 39.01 | G817: 1 | H817: Credit card | I817: 4.7
A818: 3/13/2024 | B818: Queens | C818: Normal | D818: Male | E818: Fashion & Accs | F818: 56.5 | G818: 1 | H818: Ewallet | I818: 9.6
A819: 3/13/2024 | B819: Manhattan | C819: Normal | D819: Female | E819: Food & Beverages | F819: 54.27 | G819: 5 | H819: Ewallet | I819: 4.6
A820: 3/13/2024 | B820: Brooklyn | C820: Member | D820: Female | E820: Fashion & Accs | F820: 38.3 | G820: 4 | H820: Cash | I820: 5.7
A821: 3/13/2024 | B821: Manhattan | C821: Member | D821: Male | E821: Health & Beauty | F821: 15.87 | G821: 10 | H821: Cash | I821: 5.8
A822: 3/13/2024 | B822: Manhattan | C822: Normal | D822: Male | E822: Food & Beverages | F822: 45.79 | G822: 7 | H822: Credit card | I822: 7
A823: 3/13/2024 | B823: Queens | C823: Member | D823: Male | E823: Sports & Travel | F823: 72.88 | G823: 2 | H823: Cash | I823: 6.1
A824: 3/13/2024 | B824: Brooklyn | C824: Normal | D824: Male | E824: Health & Beauty | F824: 18.11 | G824: 10 | H824: Ewallet | I824: 5.9
A825: 3/13/2024 | B825: Brooklyn | C825: Normal | D825: Female | E825: Fashion & Accs | F825: 34.7 | G825: 2 | H825: Ewallet | I825: 8.2
A826: 3/13/2024 | B826: Queens | C826: Member | D826: Male | E826: Home & Lifestyle | F826: 63.91 | G826: 8 | H826: Credit card | I826: 4.6
A827: 3/13/2024 | B827: Queens | C827: Normal | D827: Female | E827: Fashion & Accs | F827: 12.19 | G827: 8 | H827: Ewallet | I827: 6.8
A828: 3/14/2024 | B828: Queens | C828: Normal | D828: Female | E828: Electronics | F828: 51.32 | G828: 9 | H828: Cash | I828: 5.6
A829: 3/14/2024 | B829: Queens | C829: Member | D829: Male | E829: Sports & Travel | F829: 42.85 | G829: 1 | H829: Credit card | I829: 9.3
... A1009: 3/30/2024 | B1009: Queens | C1009: Normal | D1009: Male | E1009: Health & Beauty | F1009: 70.21 | G1009: 6 | H1009: Cash | I1009: 7.4
A1010: 45295 | B1010: Queens | C1010: Member | D1010: Male | E1010: Electronics | F1010: 37.06 | G1010: 4 | H1010: Ewallet | I1010: 9.7
A1011: 45295 | B1011: Brooklyn | C1011: Member | D1011: Male | E1011: Electronics | F1011: 87.87 | G1011: 9 | H1011: Ewallet | I1011: 5.6
A1012: 45295 | B1012: Brooklyn | C1012: Normal | D1012: Male | E1012: Electronics | F1012: 45.35 | G1012: 6 | H1012: Ewallet | I1012: 6.1
A1013: 45295 | B1013: Manhattan | C1013: Member | D1013: Male | E1013: Electronics | F1013: 66.35 | G1013: 1 | H1013: Credit card | I1013: 9.7
A1014: 45295 | B1014: Queens | C1014: Member | D1014: Female | E1014: Food & Beverages | F1014: 87.48 | G1014: 6 | H1014: Ewallet | I1014: 5.1
A1015: 45295 | B1015: Manhattan | C1015: Member | D1015: Female | E1015: Food & Beverages | F1015: 14.23 | G1015: 5 | H1015: Credit card | I1015: 4.4
A1016: 45295 | B1016: Queens | C1016: Normal | D1016: Female | E1016: Electronics | F1016: 23.07 | G1016: 9 | H1016: Cash | I1016: 4.9
A1017: 45295 | B1017: Queens | C1017: Member | D1017: Female | E1017: Home & Lifestyle | F1017: 80.79 | G1017: 9 | H1017: Credit card | I1017: 9.5
A1018: 45295 | B1018: Brooklyn | C1018: Member | D1018: Female | E1018: Electronics | F1018: 26.26 | G1018: 7 | H1018: Cash | I1018: 9.9
A1019: 45295 | B1019: Queens | C1019: Normal | D1019: Female | E1019: Fashion & Accs | F1019: 62.18 | G1019: 10 | H1019: Ewallet | I1019: 6
A1020: 45295 | B1020: Brooklyn | C1020: Normal | D1020: Male | E1020: Fashion & Accs | F1020: 69.08 | G1020: 2 | H1020: Credit card | I1020: 6.9
A1021: 45295 | B1021: Manhattan | C1021: Member | D1021: Female | E1021: Health & Beauty | F1021: 77.68 | G1021: 4 | H1021: Cash | I1021: 8.4
... A1242: 45630 | B1242: Queens | C1242: Normal | D1242: Male | E1242: Health & Beauty | F1242: 70.21 | G1242: 6 | H1242: Cash | I1242: 7.4
A1243: 4/13/2024 | B1243: Brooklyn | C1243: Normal | D1243: Male | E1243: Fashion & Accs | F1243: 69.08 | G1243: 2 | H1243: Credit card | I1243: 6.9
A1244: 4/13/2024 | B1244: Brooklyn | C1244: Normal | D1244: Male | E1244: Electronics | F1244: 45.35 | G1244: 6 | H1244: Ewallet | I1244: 6.1
A1245: 4/13/2024 | B1245: Manhattan | C1245: Member | D1245: Male | E1245: Electronics | F1245: 66.35 | G1245: 1 | H1245: Credit card | I1245: 9.7
A1246: 4/13/2024 | B1246: Queens | C1246: Member | D1246: Female | E1246: Food & Beverages | F1246: 87.48 | G1246: 6 | H1246: Ewallet | I1246: 5.1
A1247: 4/13/2024 | B1247: Manhattan | C1247: Member | D1247: Female | E1247: Food & Beverages | F1247: 14.23 | G1247: 5 | H1247: Credit card | I1247: 4.4
A1248: 4/13/2024 | B1248: Manhattan | C1248: Member | D1248: Male | E1248: Sports & Travel | F1248: 69.52 | G1248: 7 | H1248: Credit card | I1248: 8.5
A1249: 4/13/2024 | B1249: Queens | C1249: Normal | D1249: Female | E1249: Electronics | F1249: 23.07 | G1249: 9 | H1249: Cash | I1249: 4.9
A1250: 4/13/2024 | B1250: Queens | C1250: Member | D1250: Female | E1250: Home & Lifestyle | F1250: 80.79 | G1250: 9 | H1250: Credit card | I1250: 9.5
...

Sheet BRANCH
A3: Row Labels | B3: Sum of Total Amount
A4: Brooklyn | B4: 31603.057 | D4: =GETPIVOTDATA("Total Amount",$A$3) -> 82542.463
A5: Manhattan | B5: 22105.671
A6: Queens | B6: 28833.735
A7: Grand Total | B7: 82542.463

Sheet PRODUCT LINE
A3: Row Labels | B3: Sum of Total Amount
A4: Health & Beauty | B4: 82542.464
A5: Grand Total | B5: 82542.464

Sheet QUANTITY SOLD
A3: Row Labels | B3: Sum of Quantity
A4: Health & Beauty | B4: 1889
A5: Grand Total | B5: 1889
E10: =GETPIVOTDATA("Quantity",$A$3) -> 1889

Sheet MONTHLY
A3: Row Labels | B3: Sum of Total Amount
A4: January | B4: 117505.66
A5: February | B5: 95596.838
A6: March | B6: 99986.809
A7: April | B7: 104747.52
A8: May | B8: 78292.911
A9: June | B9: 48279.824
A10: July | B10: 43251.678
A11: August | B11: 46383.565
A12: September | B12: 79816.67
A13: October | B13: 82799.153
A14: November | B14: 97700.131
A15: December | B15: 116015.02
A16: Grand Total | B16: 1010375.8

Sheet GENDER
A3: Row Labels | B3: Sum of Total Amount
A4: Female | B4: 33298.933
A5: Male | B5: 49243.53
A6: Grand Total | B6: 82542.463

Sheet RATING
A3: Row Labels | B3: Average of Rating
A4: Health & Beauty | B4: 6.8910941
A5: Grand Total | B5: 6.8910941
C13: =GETPIVOTDATA("Rating",$A$3) -> 6.8910941

Sheet SUPER MARKET
A1: Date | B1: Month | C1: Branch | D1: Customer Type | E1: Gender | F1: Product Line | G1: Unit Price | H1: Quantity | I1: Payment | J1: Rating | K1: Gross Amount | L1: Tax % | M1: Tax Amount | N1: Total Amount
A2: 45292 | B2: =TEXT(A2,"mmmm") -> January | C2: Brooklyn | D2: Member | E2: Female | F2: Food & Beverages | G2: 84.63 | H2: 10 | I2: Credit Card | J2: 9 | K2: =G2*H2 -> 846.3 | L2: =IF(F2="electronics",18%,5%) -> 0.05 | M2: =K2*L2 -> 42.315 | N2: =K2+M2 -> 888.615
A3: 45292 | B3: =TEXT(A3,"mmmm") -> January | C3: Queens | D3: Normal | E3: Female | F3: Electronics | G3: 63.22 | H3: 2 | I3: Cash | J3: 8.5 | K3: =G3*H3 -> 126.44 | L3: =IF(F3="electronics",18%,5%) -> 0.18 | M3: =K3*L3 -> 22.7592 | N3: =K3+M3 -> 149.1992
A4: 45292 | B4: =TEXT(A4,"mmmm") -> January | C4: Brooklyn | D4: Normal | E4: Female | F4: Electronics | G4: 74.71 | H4: 6 | I4: Cash | J4: 6.7 | K4: =G4*H4 -> 448.26 | L4: =IF(F4="electronics",18%,5%) -> 0.18 | M4: =K4*L4 -> 80.6868 | N4: =K4+M4 -> 528.9468
A5: 45292 | B5: =TEXT(A5,"mmmm") -> January | C5: Queens | D5: Member | E5: Female | F5: Sports & Travel | G5: 36.98 | H5: 10 | I5: Credit Card | J5: 7 | K5: =G5*H5 -> 369.8 | L5: =IF(F5="electronics",18%,5%) -> 0.05 | M5: =K5*L5 -> 18.49 | N5: =K5+M5 -> 388.29
A6: 45292 | B6: =TEXT(A6,"mmmm") -> January | C6: Manhattan | D6: Member | E6: Female | F6: Sports & Travel | G6: 27.04 | H6: 4 | I6: Ewallet | J6: 6.9 | K6: =G6*H6 -> 108.16 | L6: =IF(F6="electronics",18%,5%) -> 0.05 | M6: =K6*L6 -> 5.408 | N6: =K6+M6 -> 113.568
A7: 45292 | B7: =TEXT(A7,"mmmm") -> January | C7: Manhattan | D7: Normal | E7: Female | F7: Fashion & Accs | G7: 65.74 | H7: 9 | I7: Cash | J7: 7.7 | K7: =G7*H7 -> 591.66 | L7: =IF(F7="electronics",18%,5%) -> 0.05 | M7: =K7*L7 -> 29.583 | N7: =K7+M7 -> 621.243
A8: 45292 | B8: =TEXT(A8,"mmmm") -> January | C8: Manhattan | D8: Member | E8: Male | F8: Home & Lifestyle | G8: 47.59 | H8: 8 | I8: Cash | J8: 5.7 | K8: =G8*H8 -> 380.72 | L8: =IF(F8="electronics",18%,5%) -> 0.05 | M8: =K8*L8 -> 19.036 | N8: =K8+M8 -> 399.756
A9: 45292 | B9: =TEXT(A9,"mmmm") -> January | C9: Manhattan | D9: Normal | E9: Male | F9: Sports & Travel | G9: 72.61 | H9: 6 | I9: Credit Card | J9: 6.9 | K9: =G9*H9 -> 435.66 | L9: =IF(F9="electronics",18%,5%) -> 0.05 | M9: =K9*L9 -> 21.783 | N9: =K9+M9 -> 457.443
A10: 45292 | B10: =TEXT(A10,"mmmm") -> January | C10: Queens | D10: Normal | E10: Male | F10: Health & Beauty | G10: 62.87 | H10: 2 | I10: Cash | J10: 5 | K10: =G10*H10 -> 125.74 | L10: =IF(F10="electronics",18%,5%) -> 0.05 | M10: =K10*L10 -> 6.287 | N10: =K10+M10 -> 132.027
A11: 45292 | B11: =TEXT(A11,"mmmm") -> January | C11: Brooklyn | D11: Normal | E11: Male | F11: Food & Beverages | G11: 21.12 | H11: 8 | I11: Cash | J11: 6.3 | K11: =G11*H11 -> 168.96 | L11: =IF(F11="electronics",18%,5%) -> 0.05 | M11: =K11*L11 -> 8.448 | N11: =K11+M11 -> 177.408
A12: 45292 | B12: =TEXT(A12,"mmmm") -> January | C12: Queens | D12: Member | E12: Female | F12: Sports & Travel | G12: 29.22 | H12: 6 | I12: Ewallet | J12: 5 | K12: =G12*H12 -> 175.32 | L12: =IF(F12="electronics",18%,5%) -> 0.05 | M12: =K12*L12 -> 8.766 | N12: =K12+M12 -> 184.086
A13: 45292 | B13: =TEXT(A13,"mmmm") -> January | C13: Manhattan | D13: Member | E13: Female | F13: Electronics | G13: 74.22 | H13: 10 | I13: Credit Card | J13: 4.3 | K13: =G13*H13 -> 742.2 | L13: =IF(F13="electronics",18%,5%) -> 0.18 | M13: =K13*L13 -> 133.596 | N13: =K13+M13 -> 875.796
... A5054: 45657 | B5054: =TEXT(A5054,"mmmm") -> December | C5054: Queens | D5054: Normal | E5054: Female | F5054: Health & Beauty | G5054: 49.75 | H5054: 7 | I5054: Cash | J5054: 5.8 | K5054: =G5054*H5054 -> 348.25 | L5054: =IF(F5054="electronics",18%,5%) -> 0.05 | M5054: =K5054*L5054 -> 17.4125 | N5054: =K5054+M5054 -> 365.6625

Sheet CHANGELOG
B3: DATA CLEANING
B5: • No duplicate records found :-To avoid same record repetition and incorrect analysis
B6: • No blanks or missing values found :- To prevent errors during data analysis and calculations
B7: • Standardized column names :- For better visualization and improve readability
B8: • Standardized payment column :- Applied the PROPER function to the payment column to make the data consistent and properly formatted
B9: • Standardized data types of columns :- To ensure each column contains the correct type of data and to avoid errors in calculations and analysis
C10: Date : General Short date
C11: Branch : General Text
C12: Customer Type : General Text
C13: Gender:General Text
C14: Product Line:General Text
C15: Unit Price:General Currency
C16: Quantity:General Number
C17: Payment: General Text
C18: Rating: General Number
C19: Gross Amount : General Currency
C20: Tax % : General Percentage
C21: Tax Amount : General Currency
C22: Total Amount : General Currency
B23: • Applied 2 decimal places to currency coulmns :- To maintain consistent formatting and improve readability
B24: • Adjusted column width using Alt + H + O + I :- To improve readability and visualization
B25: • Row height was already properly aligned,so no changes were required
B27: COLUMN CREATION
B29: • Added Gross Amount column :- To calculate the total value of products before applying tax
D30: Formula :- Unit Price * Quantity
B31: • Added Tax % column :- To record the applicable GST rate for each Product line
D32: Formula :- (=if(Product line ="electronics",18%,5%)
B33: • Added Tax Amount column :- | E33: To calculate the amount of tax applied to each transaction
D34: Formula :- Gross Amount * Tax %
B35: • Added Total Amount column :- To calculate the final transaction value after adding tax
D36: Formula :- Gross Amount + Tax Amount
B38: HEADING STYLING
B40: To make the headings clear and easy to identify
C41: • Styled the column headings by applying bold text
C42: • Applied a backround fill color to the column headings (Light blue)
C43: • Freeze top row :- To keep the column headings visible while scrolling through large amount of data

Sheet QUESTIONS
C2: ANALYSIS QUESTIONS
B3: 1 | C3: Which customer type contributes the highest total revenue?
B4: 2 | C4: What is the average rating for each branch?
B5: 3 | C5: Which payment method is most frequently used?
B6: 4 | C6: Which customer type has the highest number of transactions?
B7: 5 | C7: What is the total gross income generated by each product line?
B8: 6 | C8: What is the total number of transactions in each branch?
B9: 7 | C9: Which product line has the highest average quantity per transaction?
C12: DASHBOARD QUESTIONS
B13: 1 | C13: What is the total sales amount for each branch?
B14: 2 | C14: Which product line contributes the most to total sales?
B15: 3 | C15: Which month has the highest sale?
B16: 4 | C16: Which product line has the highest quantity sold?
B17: 5 | C17: Which product line receives the highest average rating?
B18: 6 | C18: What is the sales distribution between male &female customers?

Sheet DASHBOARD
A1: SUPER MARKET

Sheet ANALYSIS
C2: ANSWERS
B4: 1 | C4: Customer Type
C5: Normal | D5: =SUMIF('SUPER MARKET'!$D$2:$D$5054,ANALYSIS!$C5,'SUPER MARKET'!$N$2:$N$5054) -> 542448.36
C6: Member | D6: =SUMIF('SUPER MARKET'!$D$2:$D$5054,ANALYSIS!$C6,'SUPER MARKET'!$N$2:$N$5054) -> 467927.42
C7: Normal customers contribute the highest total revenue
B9: 2 | C9: Average rating for each branch
C10: Brooklyn | D10: =AVERAGEIF('SUPER MARKET'!$C$2:$C$5054,ANALYSIS!$C10,'SUPER MARKET'!$J$2:$J$5054) -> 6.871333
C11: Manhattan | D11: =AVERAGEIF('SUPER MARKET'!$C$2:$C$5054,ANALYSIS!$C11,'SUPER MARKET'!$J$2:$J$5054) -> 6.9090909
C12: Queens | D12: =AVERAGEIF('SUPER MARKET'!$C$2:$C$5054,ANALYSIS!$C12,'SUPER MARKET'!$J$2:$J$5054) -> 6.8711897
B14: 3 | C14: Payment Method
C15: Cash | D15: =COUNTIF('SUPER MARKET'!$I$2:$I$5054,ANALYSIS!$C15) -> 1674
C16: Credit Card | D16: =COUNTIF('SUPER MARKET'!$I$2:$I$5054,ANALYSIS!$C16) -> 1594
C17: Ewallet | D17: =COUNTIF('SUPER MARKET'!$I$2:$I$5054,ANALYSIS!$C17) -> 1785
C18: Ewallet is the most frequently used payment method
B20: 4 | C20: Customer Type
C21: Normal | D21: =COUNTIF('SUPER MARKET'!$D$2:$D$5054,ANALYSIS!$C21) -> 2968
C22: Member | D22: =COUNTIF('SUPER MARKET'!$D$2:$D$5054,ANALYSIS!$C22) -> 2085
C23: Normal customers have the highest number of transactions
B25: 5 | C25: Total gross income generated by each product line
C26: Electronics | D26: =SUMIF('SUPER MARKET'!$F$2:$F$5054,ANALYSIS!$C26,'SUPER MARKET'!$K$2:$K$5054) -> 159259.1
C27: Fashion & Accs | D27: =SUMIF('SUPER MARKET'!$F$2:$F$5054,ANALYSIS!$C27,'SUPER MARKET'!$K$2:$K$5054) -> 101843.91
C28: Food & Beverages | D28: =SUMIF('SUPER MARKET'!$F$2:$F$5054,ANALYSIS!$C28,'SUPER MARKET'!$K$2:$K$5054) -> 151357.73
C29: Health & Beauty | D29: =SUMIF('SUPER MARKET'!$F$2:$F$5054,ANALYSIS!$C29,'SUPER MARKET'!$K$2:$K$5054) -> 168570.61
C30: Home & Lifestyle | D30: =SUMIF('SUPER MARKET'!$F$2:$F$5054,ANALYSIS!$C30,'SUPER MARKET'!$K$2:$K$5054) -> 197260.56
C31: Sports & Travel | D31: =SUMIF('SUPER MARKET'!$F$2:$F$5054,ANALYSIS!$C31,'SUPER MARKET'!$K$2:$K$5054) -> 164252.94
B33: 6 | C33: Total number of transactions in each branch
C34: Brooklyn | D34: =COUNTIF('SUPER MARKET'!$C$2:$C$5054,ANALYSIS!$C34) -> 1793
C35: Manhattan | D35: =COUNTIF('SUPER MARKET'!$C$2:$C$5054,ANALYSIS!$C35) -> 1705
C36: Queens | D36: =COUNTIF('SUPER MARKET'!$C$2:$C$5054,ANALYSIS!$C36) -> 1555
B38: 7 | C38: Product Line
C39: Electronics | D39: =AVERAGEIF('SUPER MARKET'!$F$2:$F$5054,ANALYSIS!$C39,'SUPER MARKET'!$H$2:$H$5054) -> 5
C40: Fashion & Accs | D40: =AVERAGEIF('SUPER MARKET'!$F$2:$F$5054,ANALYSIS!$C40,'SUPER MARKET'!$H$2:$H$5054) -> 4.6198225
C41: Food & Beverages | D41: =AVERAGEIF('SUPER MARKET'!$F$2:$F$5054,ANALYSIS!$C41,'SUPER MARKET'!$H$2:$H$5054) -> 4.3766467
C42: Health & Beauty | D42: =AVERAGEIF('SUPER MARKET'!$F$2:$F$5054,ANALYSIS!$C42,'SUPER MARKET'!$H$2:$H$5054) -> 4.4843424
C43: Home & Lifestyle | D43: =AVERAGEIF('SUPER MARKET'!$F$2:$F$5054,ANALYSIS!$C43,'SUPER MARKET'!$H$2:$H$5054) -> 4.8884181
C44: Sports & Travel | D44: =AVERAGEIF('SUPER MARKET'!$F$2:$F$5054,ANALYSIS!$C44,'SUPER MARKET'!$H$2:$H$5054) -> 4.6822917
C45: Electronics has the highest average quantity per transaction
